PySAG/__init__.py
PySAG/crossover.py
PySAG/exceptions.py
PySAG/ga.py
PySAG/initialization.py
PySAG/mutation.py
PySAG/selection.py
pysag_udec-0.1.2.dist-info/licenses/LICENSE
pysag_udec-0.1.2.dist-info/METADATA
pysag_udec-0.1.2.dist-info/WHEEL
pysag_udec-0.1.2.dist-info/top_level.txt
pysag_udec-0.1.2.dist-info/RECORD
